wellally/__init__.py
wellally/common.py
wellally/family_health.py
wellally/health.py
wellally/imaging_report.py
wellally/lab_report.py
wellally/medication.py
wellally-0.1.0.dist-info/METADATA
wellally-0.1.0.dist-info/WHEEL
wellally-0.1.0.dist-info/top_level.txt
wellally-0.1.0.dist-info/RECORD
