Metadata-Version: 2.4
Name: wellally
Version: 0.1.0
Summary: Health data models for WellAlly platform
Author-email: WellAlly Team <huifer97@163.com>
License: MIT
Project-URL: Homepage, https://www.wellally.tech/
Project-URL: Documentation, https://www.wellally.tech/blog
Project-URL: Repository, https://github.com/huifer/wellally-schemas
Project-URL: Bug Reports, https://github.com/huifer/wellally-schemas/issues
Keywords: health,healthcare,fhir,hl7,medical,ehr
Classifier: Development Status :: 3 - Alpha
Classifier: Intended Audience :: Healthcare Industry
Classifier: Intended Audience :: Developers
Classifier: Topic :: Software Development :: Libraries :: Python Modules
Classifier: Topic :: Scientific/Engineering :: Medical Science Apps.
Classifier: License :: OSI Approved :: MIT License
Classifier: Programming Language :: Python :: 3
Classifier: Programming Language :: Python :: 3.8
Classifier: Programming Language :: Python :: 3.9
Classifier: Programming Language :: Python :: 3.10
Classifier: Programming Language :: Python :: 3.11
Classifier: Programming Language :: Python :: 3.12
Requires-Python: >=3.8
